tkinter_mcp/__init__.py
tkinter_mcp/launcher.py
tkinter_mcp/main.py
tkinter_mcp/py.typed
tkinter_mcp/agent/__init__.py
tkinter_mcp/agent/patcher.py
tkinter_mcp/agent/socket_server.py
tkinter_mcp/bridge/__init__.py
tkinter_mcp/bridge/app_bridge.py
tkinter_mcp/bridge/protocol.py
tkinter_mcp/bridge/remote.py
tkinter_mcp/bridge/thread_safe.py
tkinter_mcp/introspection/__init__.py
tkinter_mcp/introspection/models.py
tkinter_mcp/introspection/screenshot.py
tkinter_mcp/introspection/serializer.py
tkinter_mcp/server/__init__.py
tkinter_mcp/server/mcp_server.py
tkinter_mcp_server-0.9.3.dist-info/METADATA
tkinter_mcp_server-0.9.3.dist-info/WHEEL
tkinter_mcp_server-0.9.3.dist-info/entry_points.txt
tkinter_mcp_server-0.9.3.dist-info/licenses/LICENSE
tkinter_mcp_server-0.9.3.dist-info/RECORD
