Metadata-Version: 2.4
Name: tkinter-mcp-server
Version: 0.9.3
Summary: MCP server for inspecting and automating Tkinter GUI applications
Project-URL: Homepage, https://github.com/tctibbs/tkinter-mcp-server
Project-URL: Repository, https://github.com/tctibbs/tkinter-mcp-server
Project-URL: Issues, https://github.com/tctibbs/tkinter-mcp-server/issues
Author: Tristan Tibbs
License: MIT
License-File: LICENSE
Keywords: ai-agents,claude,gui-automation,llm,mcp,model-context-protocol,tkinter
Classifier: Development Status :: 5 - Production/Stable
Classifier: Intended Audience :: Developers
Classifier: License :: OSI Approved :: MIT License
Classifier: Operating System :: OS Independent
Classifier: Programming Language :: Python :: 3
Classifier: Programming Language :: Python :: 3.10
Classifier: Programming Language :: Python :: 3.11
Classifier: Programming Language :: Python :: 3.12
Classifier: Programming Language :: Python :: 3.13
Classifier: Topic :: Software Development :: Testing
Classifier: Topic :: Software Development :: User Interfaces
Requires-Python: >=3.10
Requires-Dist: fastmcp>=2.0.0
Requires-Dist: pillow>=10.0.0
Requires-Dist: pyautogui>=0.9.54
Provides-Extra: dev
Requires-Dist: pytest-cov>=4.0.0; extra == 'dev'
Requires-Dist: pytest-mock>=3.10.0; extra == 'dev'
Requires-Dist: pytest>=7.0.0; extra == 'dev'
Requires-Dist: ruff>=0.1.0; extra == 'dev'
